wallapopy/__init__.py
wallapopy/client.py
wallapopy/request_builder.py
wallapopy-1.0.3.dist-info/DESCRIPTION.rst
wallapopy-1.0.3.dist-info/METADATA
wallapopy-1.0.3.dist-info/RECORD
wallapopy-1.0.3.dist-info/WHEEL
wallapopy-1.0.3.dist-info/metadata.json
wallapopy-1.0.3.dist-info/top_level.txt
